aws_s3_risk_footprint/__init__.py
aws_s3_risk_footprint/cli.py
aws_s3_risk_footprint/s3_risk.py
aws_s3_risk_footprint/s3_scan.py
aws_s3_risk_footprint-0.1.8.dist-info/licenses/LICENSE
aws_s3_risk_footprint-0.1.8.dist-info/METADATA
aws_s3_risk_footprint-0.1.8.dist-info/WHEEL
aws_s3_risk_footprint-0.1.8.dist-info/entry_points.txt
aws_s3_risk_footprint-0.1.8.dist-info/top_level.txt
aws_s3_risk_footprint-0.1.8.dist-info/RECORD
