Metadata-Version: 2.4
Name: aws-s3-risk-footprint
Version: 0.1.8
Summary: A CLI tool to analyze AWS S3 regional distribution and security risk
License: MIT
Requires-Python: >=3.10
License-File: LICENSE
Dynamic: license-file
